voxelamming/__init__.py
voxelamming/map_util.py
voxelamming/matrix_util.py
voxelamming/ply_util.py
voxelamming/turtle.py
voxelamming/voxelamming.py
voxelamming-0.3.4.dist-info/LICENSE.txt
voxelamming-0.3.4.dist-info/METADATA
voxelamming-0.3.4.dist-info/WHEEL
voxelamming-0.3.4.dist-info/top_level.txt
voxelamming-0.3.4.dist-info/RECORD
