Metadata-Version: 2.1
Name: voxelamming
Version: 0.3.4
Summary: Convert Python code to JSON and send it to the Voxelamming app.
Author: creativival
Classifier: Development Status :: 3 - Alpha
Classifier: Programming Language :: Python :: 3
Classifier: License :: OSI Approved :: MIT License
Classifier: Operating System :: OS Independent
Requires-Python: >=3.9
License-File: LICENSE.txt
Requires-Dist: websocket-client
